dl24_dash/__init__.py
dl24_dash/conf.py
dl24_dash/main.py
dl24_dash/apps/__init__.py
dl24_dash/apps/monitor.py
dl24_dash/apps/plot.py
dl24_dash/dl24/__init__.py
dl24_dash/dl24/crc.py
dl24_dash/dl24/dl24.py
dl24_dash/dl24/dl24_data_store.py
dl24_dash/plotting/__init__.py
dl24_dash/plotting/plotting.py
dl24_dash-0.1.3.dist-info/licenses/LICENSE
dl24_dash-0.1.3.dist-info/METADATA
dl24_dash-0.1.3.dist-info/WHEEL
dl24_dash-0.1.3.dist-info/entry_points.txt
dl24_dash-0.1.3.dist-info/top_level.txt
dl24_dash-0.1.3.dist-info/RECORD
