Metadata-Version: 2.4
Name: dl24-dash
Version: 0.1.3
Summary: A tool for DL24 electronic load device with support for data visualization using dash.
Requires-Python: >=3.11
License-File: LICENSE
Requires-Dist: pyserial>=3.5
Requires-Dist: plotly>=5.23.0
Requires-Dist: numpy>=2.1.0
Requires-Dist: polars>=1.5.0
Requires-Dist: dash>=2.17.1
Requires-Dist: typer>=0.12.4
Requires-Dist: rich>=13.7.1
Requires-Dist: pydantic>=2.8.2
Provides-Extra: build
Requires-Dist: setuptools; extra == "build"
Dynamic: license-file
